sphinx_rst_builder/__init__.py
sphinx_rst_builder/_builder.py
sphinx_rst_builder/_writer.py
sphinx_rst_builder-0.0.3.dist-info/LICENSE.rst
sphinx_rst_builder-0.0.3.dist-info/METADATA
sphinx_rst_builder-0.0.3.dist-info/WHEEL
sphinx_rst_builder-0.0.3.dist-info/top_level.txt
sphinx_rst_builder-0.0.3.dist-info/zip-safe
sphinx_rst_builder-0.0.3.dist-info/RECORD
