Metadata-Version: 2.1
Name: sphinx-rst-builder
Version: 0.0.3
Summary: Sphinx reStructuredText builder
Home-page: https://github.com/davidfritzsche/sphinx-rst-builder
Maintainer: David Fritzsche
Maintainer-email: david.fritzsche@mvua.de
License: BSD-2-Clause
Platform: any
Classifier: Development Status :: 4 - Beta
Classifier: Environment :: Console
Classifier: Framework :: Sphinx :: Extension
Classifier: Intended Audience :: Developers
Classifier: License :: OSI Approved :: BSD License
Classifier: Operating System :: OS Independent
Classifier: Programming Language :: Python
Classifier: Topic :: Documentation :: Sphinx
Classifier: Topic :: Software Development :: Documentation
Classifier: Topic :: Text Processing :: Markup
Classifier: Programming Language :: Python :: 3 :: Only
Classifier: Programming Language :: Python :: 3.6
Classifier: Programming Language :: Python :: 3.7
Classifier: Programming Language :: Python :: 3.8
Classifier: Typing :: Typed
Requires-Python: >=3.6
Requires-Dist: sphinx (>=2)
